flake8_context_manager_scope/__init__.py
flake8_context_manager_scope/checker.py
flake8_context_manager_scope-0.1.0.dist-info/METADATA
flake8_context_manager_scope-0.1.0.dist-info/WHEEL
flake8_context_manager_scope-0.1.0.dist-info/entry_points.txt
flake8_context_manager_scope-0.1.0.dist-info/licenses/LICENSE
flake8_context_manager_scope-0.1.0.dist-info/RECORD
