Metadata-Version: 2.4
Name: flake8-context-manager-scope
Version: 0.1.0
Summary: Flake8 plugin to detect context manager variables used outside their scope
License-File: LICENSE
Requires-Python: >=3.11
Requires-Dist: flake8>=6.0.0
